.gitignore
README.md
setup.py
src/bellande_format.egg-info/PKG-INFO
src/bellande_format.egg-info/SOURCES.txt
src/bellande_format.egg-info/dependency_links.txt
src/bellande_format.egg-info/entry_points.txt
src/bellande_format.egg-info/requires.txt
src/bellande_format.egg-info/top_level.txt
src/bellande_parser/__init__.py
src/bellande_parser/bellande_parser.py