Metadata-Version: 2.1
Name: bellande_format
Version: 0.1.8
Summary: Bellande Format is a file format type
Author: RonaldsonBellande
Author-email: ronaldsonbellande@gmail.com
Project-URL: Home, https://github.com/Architecture-Mechanism/bellande_format
Project-URL: Homepage, https://github.com/Architecture-Mechanism/bellande_format
Project-URL: Documentation, https://github.com/Architecture-Mechanism/bellande_format
Project-URL: Repository, https://github.com/Architecture-Mechanism/bellande_format
Keywords: package,setuptools,bellande,format
Classifier: License :: OSI Approved :: GNU General Public License v3 (GPLv3)
Classifier: Programming Language :: Python
Classifier: Programming Language :: Python :: 3
Classifier: Programming Language :: Python :: 3.6
Classifier: Programming Language :: Python :: 3.7
Classifier: Programming Language :: Python :: 3.8
Classifier: Programming Language :: Python :: 3.9
Requires-Python: >=3.6
Requires-Dist: numpy>=1.18.0
Requires-Dist: typing-extensions>=3.7.4
Provides-Extra: dev
Requires-Dist: pytest; extra == "dev"
Requires-Dist: pytest-cov[all]; extra == "dev"
Requires-Dist: mypy; extra == "dev"
Requires-Dist: black; extra == "dev"
